mmic/__init__.py
mmic/_version.py
mmic/mmic.py
mmic/components/__init__.py
mmic/components/base/__init__.py
mmic/components/base/base_component.py
mmic/components/base/config.py
mmic/components/blueprints/__init__.py
mmic/components/blueprints/generic_component.py
mmic/components/blueprints/strategy_component.py
mmic/components/blueprints/tactic_component.py
mmic/data/README.md
mmic/data/look_and_say.dat
mmic/data/imgs/mm_component_diagram.png
mmic/data/imgs/mm_component_hierarchy.png
mmic/tests/__init__.py
mmic/tests/test_base_components.py
mmic/tests/test_blueprint_components.py
mmic-0.1.1.dist-info/LICENSE
mmic-0.1.1.dist-info/METADATA
mmic-0.1.1.dist-info/WHEEL
mmic-0.1.1.dist-info/top_level.txt
mmic-0.1.1.dist-info/RECORD
