Metadata-Version: 2.1
Name: mmic
Version: 0.1.1
Summary: UNKNOWN
Home-page: https://github.com/MolSSI/mmic
Author: MolSSI
Author-email: mmic@molssi.org
License: BSD-3-Clause
Platform: UNKNOWN
Classifier: Development Status :: 3 - Alpha
License-File: LICENSE
Requires-Dist: pydantic
Requires-Dist: cmselemental (==0.2.0)
